mdconverter/__init__.py
mdconverter/containers.py
mdconverter/documents.py
mdconverter/environments.py
mdconverter/img_tools.py
mdconverter/param.py
mdconverter/parser.py
mdconverter/utils.py
mdconverter-0.2.dev1.dist-info/METADATA
mdconverter-0.2.dev1.dist-info/RECORD
mdconverter-0.2.dev1.dist-info/WHEEL
mdconverter-0.2.dev1.dist-info/top_level.txt
